MANIFEST.in
distribute_setup.py
setup.py
Keen_SoftLayer.egg-info/PKG-INFO
Keen_SoftLayer.egg-info/SOURCES.txt
Keen_SoftLayer.egg-info/dependency_links.txt
Keen_SoftLayer.egg-info/top_level.txt
SoftLayer/API.py
SoftLayer/__init__.py