Metadata-Version: 1.0
Name: Keen-SoftLayer
Version: 1.1
Summary: A library to contact SoftLayer's backend services
Home-page: http://github.com/softlayer/softlayer-api-python-client
Author: SoftLayer Technologies, Inc.
Author-email: dan@keen.io
License: The BSD License
Platform: UNKNOWN
